cubicweb_prov/__init__.py
cubicweb_prov/__pkginfo__.py
cubicweb_prov/entities.py
cubicweb_prov/schema.py
cubicweb_prov/site_cubicweb.py
cubicweb_prov/views.py
cubicweb_prov/i18n/en.po
cubicweb_prov/i18n/fr.po
cubicweb_prov/migration/0.2.0_Any.py
cubicweb_prov/migration/0.3.0_Any.py
cubicweb_prov-1.0.0.dist-info/METADATA
cubicweb_prov-1.0.0.dist-info/WHEEL
cubicweb_prov-1.0.0.dist-info/entry_points.txt
cubicweb_prov-1.0.0.dist-info/top_level.txt
cubicweb_prov-1.0.0.dist-info/RECORD
